nirs4all/__init__.py
nirs4all/analysis/__init__.py
nirs4all/analysis/presets.py
nirs4all/analysis/results.py
nirs4all/analysis/selector.py
nirs4all/analysis/transfer_metrics.py
nirs4all/analysis/transfer_utils.py
nirs4all/api/__init__.py
nirs4all/api/explain.py
nirs4all/api/generate.py
nirs4all/api/predict.py
nirs4all/api/result.py
nirs4all/api/retrain.py
nirs4all/api/run.py
nirs4all/api/session.py
nirs4all/cli/__init__.py
nirs4all/cli/installation_test.py
nirs4all/cli/main.py
nirs4all/cli/commands/__init__.py
nirs4all/cli/commands/artifacts.py
nirs4all/cli/commands/config.py
nirs4all/cli/commands/dataset.py
nirs4all/cli/commands/workspace.py
nirs4all/config/__init__.py
nirs4all/config/validator.py
nirs4all/controllers/__init__.py
nirs4all/controllers/base.py
nirs4all/controllers/controller.py
nirs4all/controllers/presets.py
nirs4all/controllers/registry.py
nirs4all/controllers/charts/__init__.py
nirs4all/controllers/charts/augmentation.py
nirs4all/controllers/charts/exclusion.py
nirs4all/controllers/charts/folds.py
nirs4all/controllers/charts/spectra.py
nirs4all/controllers/charts/spectral_distribution.py
nirs4all/controllers/charts/targets.py
nirs4all/controllers/data/__init__.py
nirs4all/controllers/data/auto_transfer_preproc.py
nirs4all/controllers/data/balancing.py
nirs4all/controllers/data/branch.py
nirs4all/controllers/data/concat_transform.py
nirs4all/controllers/data/feature_augmentation.py
nirs4all/controllers/data/feature_selection.py
nirs4all/controllers/data/merge.py
nirs4all/controllers/data/metadata_partitioner.py
nirs4all/controllers/data/outlier_excluder.py
nirs4all/controllers/data/repetition.py
nirs4all/controllers/data/resampler.py
nirs4all/controllers/data/sample_augmentation.py
nirs4all/controllers/data/sample_filter.py
nirs4all/controllers/data/sample_partitioner.py
nirs4all/controllers/data/source_branch.py
nirs4all/controllers/flow/__init__.py
nirs4all/controllers/flow/condition.py
nirs4all/controllers/flow/dummy.py
nirs4all-0.6.1.dist-info/licenses/LICENSE
nirs4all-0.6.1.dist-info/licenses/LICENSE_FR
nirs4all-0.6.1.dist-info/METADATA
nirs4all-0.6.1.dist-info/WHEEL
nirs4all-0.6.1.dist-info/entry_points.txt
nirs4all-0.6.1.dist-info/top_level.txt
nirs4all-0.6.1.dist-info/RECORD
