Metadata-Version: 2.4
Name: nirs4all
Version: 0.6.1
Summary: A comprehensive Python library for Near-Infrared Spectroscopy (NIRS) data analysis with ML/DL pipelines.
Author-email: Gregory Beurier <beurier@cirad.fr>, Denis Cornet <denis.cornet@cirad.fr>, Lauriane Rouan <lauriane.rouan@cirad.fr>
Maintainer-email: Gregory Beurier <gregory.beurier@cirad.fr>
License: This repository (project **nirs4all**) is distributed under a **DUAL LICENSE**.
Project-URL: Homepage, https://github.com/GBeurier/nirs4all
Project-URL: Documentation, https://nirs4all.readthedocs.io
Project-URL: Repository, https://github.com/GBeurier/nirs4all
Project-URL: Issues, https://github.com/GBeurier/nirs4all/issues
Project-URL: Changelog, https://github.com/GBeurier/nirs4all/blob/main/CHANGELOG.md
Keywords: nirs,near-infrared,spectroscopy,chemometrics,machine-learning,deep-learning,preprocessing,pls,sklearn,tensorflow,pytorch,jax
Classifier: Development Status :: 4 - Beta
Classifier: Intended Audience :: Science/Research
Classifier: Intended Audience :: Developers
Classifier: License :: OSI Approved :: CEA CNRS Inria Logiciel Libre License, version 2.1 (CeCILL-2.1)
Classifier: Operating System :: OS Independent
Classifier: Programming Language :: Python :: 3
Classifier: Programming Language :: Python :: 3.11
Classifier: Programming Language :: Python :: 3.12
Classifier: Programming Language :: Python :: 3.13
Classifier: Topic :: Scientific/Engineering
Classifier: Topic :: Scientific/Engineering :: Artificial Intelligence
Classifier: Topic :: Scientific/Engineering :: Chemistry
Classifier: Typing :: Typed
Requires-Python: >=3.11
License-File: LICENSE
License-File: LICENSE_FR
Requires-Dist: numpy>=1.24.0
Requires-Dist: pandas>=2.0.0
Requires-Dist: scipy>=1.10.0
Requires-Dist: scikit-learn>=1.2.0
Requires-Dist: polars>=0.20.0
Requires-Dist: pyarrow>=14.0.0
Requires-Dist: h5py>=3.8.0
Requires-Dist: PyWavelets>=1.4.0
Requires-Dist: optuna>=3.0.0
Requires-Dist: matplotlib>=3.7.0
Requires-Dist: seaborn>=0.12.0
Requires-Dist: shap>=0.42.0
Requires-Dist: joblib>=1.2.0
Requires-Dist: jsonschema>=4.17.0
Requires-Dist: pyyaml>=6.0.0
Requires-Dist: packaging>=23.0
Requires-Dist: pydantic>=2.0.0
Requires-Dist: kennard-stone>=2.2.0
Requires-Dist: twinning>=0.0.5
Provides-Extra: tensorflow
Requires-Dist: tensorflow>=2.14.0; extra == "tensorflow"
Provides-Extra: gpu
Requires-Dist: tensorflow[and-cuda]>=2.14.0; extra == "gpu"
Provides-Extra: torch
Requires-Dist: torch>=2.1.0; extra == "torch"
Requires-Dist: tabpfn>=2.0.0; extra == "torch"
Provides-Extra: keras
Requires-Dist: keras>=3.0.0; extra == "keras"
Provides-Extra: jax
Requires-Dist: jax>=0.4.20; extra == "jax"
Requires-Dist: jaxlib>=0.4.20; extra == "jax"
Requires-Dist: flax>=0.8.0; extra == "jax"
Provides-Extra: autogluon
Requires-Dist: autogluon>=1.0.0; extra == "autogluon"
Provides-Extra: pls
Requires-Dist: ikpls>=1.1.0; extra == "pls"
Requires-Dist: pyopls>=20.0; extra == "pls"
Requires-Dist: trendfitter>=0.0.6; extra == "pls"
Provides-Extra: all
Requires-Dist: tensorflow>=2.14.0; extra == "all"
Requires-Dist: torch>=2.1.0; extra == "all"
Requires-Dist: keras>=3.0.0; extra == "all"
Requires-Dist: jax>=0.4.20; extra == "all"
Requires-Dist: jaxlib>=0.4.20; extra == "all"
Requires-Dist: flax>=0.8.0; extra == "all"
Requires-Dist: ikpls>=1.1.0; extra == "all"
Requires-Dist: pyopls>=20.0; extra == "all"
Requires-Dist: trendfitter>=0.0.6; extra == "all"
Provides-Extra: all-gpu
Requires-Dist: tensorflow[and-cuda]>=2.14.0; extra == "all-gpu"
Requires-Dist: torch>=2.1.0; extra == "all-gpu"
Requires-Dist: keras>=3.0.0; extra == "all-gpu"
Requires-Dist: jax[cuda12]>=0.4.20; extra == "all-gpu"
Requires-Dist: jaxlib>=0.4.20; extra == "all-gpu"
Requires-Dist: flax>=0.8.0; extra == "all-gpu"
Requires-Dist: ikpls>=1.1.0; extra == "all-gpu"
Requires-Dist: pyopls>=20.0; extra == "all-gpu"
Requires-Dist: trendfitter>=0.0.6; extra == "all-gpu"
Provides-Extra: dev
Requires-Dist: pytest>=7.4.0; extra == "dev"
Requires-Dist: pytest-cov>=4.1.0; extra == "dev"
Requires-Dist: pytest-xdist>=3.5.0; extra == "dev"
Requires-Dist: pytest-benchmark>=4.0.0; extra == "dev"
Requires-Dist: build>=1.0.0; extra == "dev"
Requires-Dist: ruff>=0.1.0; extra == "dev"
Requires-Dist: mypy>=1.7.0; extra == "dev"
Provides-Extra: docs
Requires-Dist: sphinx>=7.0.0; extra == "docs"
Requires-Dist: sphinx-rtd-theme>=2.0.0; extra == "docs"
Requires-Dist: myst-parser>=2.0.0; extra == "docs"
Requires-Dist: sphinx-copybutton>=0.5.0; extra == "docs"
Requires-Dist: sphinx-design>=0.5.0; extra == "docs"
Provides-Extra: reports
Requires-Dist: pypandoc>=1.12; extra == "reports"
Requires-Dist: PyPDF2>=3.0.0; extra == "reports"
Requires-Dist: pdf2image>=1.16.0; extra == "reports"
Dynamic: license-file
